zipch/__init__.py
zipch/zipcodes.py
zipch-2.0.1.dist-info/LICENSE
zipch-2.0.1.dist-info/METADATA
zipch-2.0.1.dist-info/WHEEL
zipch-2.0.1.dist-info/top_level.txt
zipch-2.0.1.dist-info/RECORD
