Metadata-Version: 2.1
Name: zipch
Version: 2.0.1
Summary: Database of zipcodes, cantons and municipalities for Switzerland
Author-email: Sylvain Fankhauser <sephi@fhtagn.top>
Project-URL: Homepage, https://github.com/sephii/zipch
Classifier: Programming Language :: Python :: 3
Classifier: License :: OSI Approved :: MIT License
Classifier: Operating System :: OS Independent
Requires-Python: >=3.7
License-File: LICENSE
